{
  "subtitle": "Como a fa\u00e7o parar?", 
  "description": "Como a fa\u00e7o parar?", 
  "language": "por_PT", 
  "title": "PAP\u00c1recente: Chora beb\u00e9 Chora", 
  "primary_category": "cf6301c3cb2b420f9e9065be7188e01e", 
  "created_at": "2014-12-23T11:37:25+00:00", 
  "featured_in_category": false, 
  "modified_at": "2015-02-10T15:27:07.132790+00:00", 
  "_version": {
    "package_version": "0.3.1", 
    "language_version": "2.7.6", 
    "language_version_string": "2.7.6 (default, Mar 22 2014, 23:03:41) \n[GCC 4.8.2]", 
    "language": "python", 
    "package": "elastic-git"
  }, 
  "linked_pages": [], 
  "id": null, 
  "content": "Apresentado pela MAMA\r\n\r\nAntes do meu beb\u00e9 ter nascido, a \u00fanica coisa de que tinha a certeza era que eu provocava o choro dos beb\u00e9s. Quantas vezes uma tia ou uma prima p\u00f4s o seu beb\u00e9 no meu colo e este come\u00e7ou a chorar? Era como se o beb\u00e9 soubesse que eu n\u00e3o estava feito para ser pai!\r\n\r\nPor isso antes do meu chegar, pensei: e se o meu beb\u00e9 fizer a mesma coisa? \r\n\r\nDecidi que n\u00e3o iria permitir que isso acontecesse. Por isso decidi investigar porque \u00e9 que os beb\u00e9s choram. Perguntei a todas as minhas tias especialistas! Disseram o seguinte: existem quatro raz\u00f5es para um beb\u00e9 chorar. Chora quando tem fome, quando tem dores, a fralda molhada ou est\u00e1 cansado.\r\n\r\nMas os beb\u00e9s podem tamb\u00e9m chorar porque est\u00e3o tristes? \r\n\r\n\u00c9 certo que podem estar contentes sem qualquer raz\u00e3o. A minha filha sorriu para mim pela primeira vez com 6 semanas de vida. Foi o meu melhor momento! Foi como se se tivesse tornado num verdadeiro ser humano naquele momento. Os beb\u00e9s sorriem para as suas m\u00e3es, para os pais e para outras pessoas que reconhecem. E depois fazem caretas, palram e riem-se. \r\n\r\nAgora passo muito tempo a fazer palha\u00e7adas para a minha filha se rir - Fa\u00e7o caretas, imito os animais, saltito como uma r\u00e3 e puxo-lhe os dedos dos p\u00e9s.\r\n\r\nQuando ela chora verifico os 4 pontos. Verifico se comeu bem, se a fralda est\u00e1 seca, se dormiu bem e se n\u00e3o sujou a fralda.\r\n\r\nQuando tenho a certeza que est\u00e1 bem, tento fazer com que ela fique mais animada. Conhe\u00e7o boas m\u00fasicas. Sou capaz de dan\u00e7ar para ela, ler uma hist\u00f3ria, fazer-lhe c\u00f3cegas nos p\u00e9s...\r\n\r\n**A MAMA ajuda: Um beb\u00e9 que chora pode causar muito stress aos pais. Primeiro deve fazer a verifica\u00e7\u00e3o dos 4 pontos do PAP\u00c1recente para ter a certeza de que o seu beb\u00e9 est\u00e1 confort\u00e1vel. Quando tiver a certeza que est\u00e1 tudo ok, ent\u00e3o \u00e9 altura de come\u00e7ar a cantar e a dan\u00e7ar!**", 
  "source": "e476c985a610436092c81558befd95d1", 
  "featured": false, 
  "author_tags": [], 
  "image": null, 
  "published": null, 
  "position": 2, 
  "image_host": "http://thumbor.unicore.io", 
  "slug": "paparecente-chora-bebe-chora", 
  "uuid": "2f97f44f788a44138e94490da90380a3"
}